orthpylib/__init__.py
orthpylib/module1.py
orthpylib/orth_tools.py
orthpylib/ws_lib.py
orthpylib-0.1.9.dist-info/licenses/LICENSE
orthpylib-0.1.9.dist-info/METADATA
orthpylib-0.1.9.dist-info/WHEEL
orthpylib-0.1.9.dist-info/top_level.txt
orthpylib-0.1.9.dist-info/RECORD
