Metadata-Version: 2.4
Name: orthpylib
Version: 0.1.9
Summary: support to get a,b,c,d matrix
Home-page: https://github.com/orthogonalpub
Author: Orthogonal
Author-email: 
Classifier: Programming Language :: Python :: 3
Classifier: License :: OSI Approved :: MIT License
Classifier: Operating System :: OS Independent
Requires-Python: >=3.8
License-File: LICENSE
Dynamic: author
Dynamic: classifier
Dynamic: description
Dynamic: description-content-type
Dynamic: home-page
Dynamic: license-file
Dynamic: requires-python
Dynamic: summary
